contentfiles/__init__.py
contentfiles/storage.py
blanc_contentfiles-0.2.6.dist-info/LICENSE
blanc_contentfiles-0.2.6.dist-info/METADATA
blanc_contentfiles-0.2.6.dist-info/WHEEL
blanc_contentfiles-0.2.6.dist-info/top_level.txt
blanc_contentfiles-0.2.6.dist-info/RECORD
